{
  "imports": {
    "class": "imports",
    "SNMPv2-CONF": [
      "OBJECT-GROUP",
      "NOTIFICATION-GROUP",
      "MODULE-COMPLIANCE"
    ],
    "SNMPv2-MIB": [
      "snmpTraps"
    ],
    "SNMPv2-SMI": [
      "iso",
      "MibIdentifier",
      "OBJECT-TYPE",
      "NOTIFICATION-TYPE",
      "Counter32",
      "Unsigned32",
      "Gauge32",
      "MODULE-IDENTITY",
      "enterprises",
      "Counter64",
      "Bits",
      "mib-2",
      "Integer32",
      "TimeTicks",
      "OBJECT-IDENTITY",
      "IpAddress"
    ],
    "SNMPv2-TC": [
      "TestAndIncr",
      "TimeStamp",
      "TEXTUAL-CONVENTION",
      "RowStatus",
      "TruthValue",
      "AutonomousType",
      "DisplayString",
      "PhysAddress"
    ]
  },
  "observium": {
    "name": "observium",
    "oid": "1.3.6.1.4.1.36602",
    "class": "objectidentity"
  },
  "obsObjects": {
    "name": "obsObjects",
    "oid": "1.3.6.1.4.1.36602.1",
    "class": "objectidentity"
  },
  "obsHostInfo": {
    "name": "obsHostInfo",
    "oid": "1.3.6.1.4.1.36602.1.1",
    "class": "objectidentity"
  },
  "obsLinuxDistro": {
    "name": "obsLinuxDistro",
    "oid": "1.3.6.1.4.1.36602.1.1.2",
    "nodetype": "scalar",
    "class": "objecttype",
    "syntax": {
      "type": "DisplayString",
      "class": "type",
      "constraints": {
        "size": [
          {
            "min": 0,
            "max": 255
          }
        ]
      }
    },
    "maxaccess": "read-only",
    "status": "current",
    "description": "Linux distribution and version"
  },
  "obsCPUUsage": {
    "name": "obsCPUUsage",
    "oid": "1.3.6.1.4.1.36602.1.1.3",
    "nodetype": "scalar",
    "class": "objecttype",
    "syntax": {
      "type": "INTEGER",
      "class": "type"
    },
    "maxaccess": "read-only",
    "status": "mandatory",
    "description": "CPU Usage"
  },
  "meta": {
    "comments": [
      "ASN.1 source file://MIBS/asn1/OBSERVIUM-MIB.mib",
      "Produced by pysmi-0.3.4 at Tue Apr 20 16:50:15 2021",
      "On host samy-ThinkPad-T495s platform Linux version 5.8.0-50-generic by user root",
      "Using Python version 3.8.5 (default, Jan 27 2021, 15:41:15) "
    ],
    "module": "OBSERVIUM-MIB"
  }
}