{
  "imports": {
    "class": "imports",
    "RFC1155-SMI": [
      "MODULE-IDENTITY"
    ],
    "SNMPv2-CONF": [
      "MODULE-COMPLIANCE",
      "NOTIFICATION-GROUP"
    ],
    "SNMPv2-SMI": [
      "Unsigned32",
      "Integer32",
      "OBJECT-IDENTITY",
      "NOTIFICATION-TYPE",
      "Counter32",
      "Bits",
      "OBJECT-TYPE",
      "Gauge32",
      "Counter64",
      "iso",
      "MibIdentifier",
      "MODULE-IDENTITY",
      "TimeTicks",
      "IpAddress",
      "enterprises"
    ],
    "SNMPv2-TC": [
      "TEXTUAL-CONVENTION",
      "DisplayString"
    ]
  },
  "veraxMIB": {
    "name": "veraxMIB",
    "oid": "1.3.6.1.4.1.21340",
    "class": "moduleidentity",
    "lastupdated": "201211051200Z",
    "organization": "Verax Systems",
    "contactinfo": "Verax Systems Corp. E-mail: office@veraxsystems.com",
    "description": "This MIB is the base Verax System MIB."
  },
  "products": {
    "name": "products",
    "oid": "1.3.6.1.4.1.21340.1",
    "class": "objectidentity"
  },
  "veraxnms": {
    "name": "veraxnms",
    "oid": "1.3.6.1.4.1.21340.1.2",
    "class": "objectidentity"
  },
  "meta": {
    "comments": [
      "ASN.1 source file://MIBS/asn1/VERAX-MIB.mib",
      "Produced by pysmi-0.3.4 at Tue Apr 20 19:50:23 2021",
      "On host samy-ThinkPad-T495s platform Linux version 5.8.0-50-generic by user root",
      "Using Python version 3.8.5 (default, Jan 27 2021, 15:41:15) "
    ],
    "module": "VERAX-MIB"
  }
}